pufftracer/__init__.py
pufftracer/honahlee.py
pufftracer/pufftrc.py
pufftracer-0.1.11.dist-info/LICENSE.txt
pufftracer-0.1.11.dist-info/METADATA
pufftracer-0.1.11.dist-info/WHEEL
pufftracer-0.1.11.dist-info/top_level.txt
pufftracer-0.1.11.dist-info/RECORD
