Metadata-Version: 2.1
Name: pufftracer
Version: 0.1.11
Summary: An alternate Programmatic Interface for tracing.
Home-page: https://github.com/DanLBates/pufftrc
Author: Daniel L. Bates
Author-email: danbates@verizon.net
License: UNKNOWN
Keywords: 'Trace','Debug','Debug Aid','Progmatic Interface Trace'
Platform: UNKNOWN
Classifier: Programming Language :: Python :: 3
Classifier: License :: OSI Approved :: MIT License
Classifier: Operating System :: OS Independent
Classifier: Intended Audience :: Developers
Requires-Python: >=3.6
License-File: LICENSE.txt
